odoo/addons/hr_timesheet_sheet_role/README.rst
odoo/addons/hr_timesheet_sheet_role/__init__.py
odoo/addons/hr_timesheet_sheet_role/__manifest__.py
odoo/addons/hr_timesheet_sheet_role/i18n/es.po
odoo/addons/hr_timesheet_sheet_role/i18n/hr_timesheet_sheet_role.pot
odoo/addons/hr_timesheet_sheet_role/models/__init__.py
odoo/addons/hr_timesheet_sheet_role/models/hr_timesheet_sheet.py
odoo/addons/hr_timesheet_sheet_role/readme/CONTRIBUTORS.rst
odoo/addons/hr_timesheet_sheet_role/readme/DESCRIPTION.rst
odoo/addons/hr_timesheet_sheet_role/static/description/icon.png
odoo/addons/hr_timesheet_sheet_role/static/description/index.html
odoo/addons/hr_timesheet_sheet_role/tests/__init__.py
odoo/addons/hr_timesheet_sheet_role/tests/test_hr_timesheet_sheet_role.py
odoo/addons/hr_timesheet_sheet_role/views/hr_timesheet_sheet.xml
odoo12_addon_hr_timesheet_sheet_role-12.0.2.2.1.dist-info/METADATA
odoo12_addon_hr_timesheet_sheet_role-12.0.2.2.1.dist-info/WHEEL
odoo12_addon_hr_timesheet_sheet_role-12.0.2.2.1.dist-info/top_level.txt
odoo12_addon_hr_timesheet_sheet_role-12.0.2.2.1.dist-info/RECORD
